logger_by_format/__init__.py
logger_by_format/logger.py
logger_by_format-0.1.dist-info/METADATA
logger_by_format-0.1.dist-info/WHEEL
logger_by_format-0.1.dist-info/top_level.txt
logger_by_format-0.1.dist-info/RECORD
